cicd_secrets_updater_lib/__init__.py
cicd_secrets_updater_lib/banner.py
cicd_secrets_updater_lib/cicd.py
cicd_secrets_updater_lib/detect_secrets.py
cicd_secrets_updater_lib/git.py
cicd_secrets_updater_lib/poetry.py
cicd_secrets_updater_lib/utilities.py
cicd_secrets_updater_lib-0.1.9.dist-info/METADATA
cicd_secrets_updater_lib-0.1.9.dist-info/WHEEL
cicd_secrets_updater_lib-0.1.9.dist-info/RECORD
