Metadata-Version: 2.1
Name: cicd-secrets-updater-lib
Version: 0.1.9
Summary: The set of reusable and modular functions used to update secrets in a CI/CD pipeline.
Author: Nicholas Adamou
Author-email: nicholas.adamou@ibm.com
Requires-Python: >=3.9,<4.0
Classifier: Programming Language :: Python :: 3
Classifier: Programming Language :: Python :: 3.9
Classifier: Programming Language :: Python :: 3.10
Classifier: Programming Language :: Python :: 3.11
Classifier: Programming Language :: Python :: 3.12
Requires-Dist: pyfiglet (>=1.0.2,<2.0.0)
Requires-Dist: pygithub (>=2.2.0,<3.0.0)
Requires-Dist: pyyaml (>=6.0.1,<7.0.0)
Requires-Dist: toml (>=0.10.2,<0.11.0)
